sinc/__init__.py
sinc/nystroem.py
sinc/ode.py
sinc/sinc.py
sinc-0.1.0.dist-info/LICENSE
sinc-0.1.0.dist-info/METADATA
sinc-0.1.0.dist-info/WHEEL
sinc-0.1.0.dist-info/top_level.txt
sinc-0.1.0.dist-info/RECORD
