Metadata-Version: 2.2
Name: sinc
Version: 0.1.0
Summary: Sinc Kernel Function
Home-page: https://github.com/alirezaafzalaghaei/sinc
Author: Alireza Afzal Aghaei
Author-email: alirezaafzalaghaei@gmail.com
License: GPL-3.0
Classifier: Programming Language :: Python :: 3.9
Classifier: Operating System :: OS Independent
Classifier: Topic :: Scientific/Engineering :: Artificial Intelligence
Classifier: Topic :: Scientific/Engineering :: Mathematics
Classifier: License :: OSI Approved :: GNU General Public License v3 (GPLv3)
License-File: LICENSE
Requires-Dist: numpy
Requires-Dist: scikit-learn
Requires-Dist: numba
Dynamic: author
Dynamic: author-email
Dynamic: classifier
Dynamic: description
Dynamic: description-content-type
Dynamic: home-page
Dynamic: license
Dynamic: requires-dist
Dynamic: summary
